jaxmesh/__init__.py
jaxmesh/py.typed
jaxmesh/_internal/__init__.py
jaxmesh/_internal/cpu_fallback.py
jaxmesh/geometry/__init__.py
jaxmesh/geometry/barycentric.py
jaxmesh/geometry/normals.py
jaxmesh/io/__init__.py
jaxmesh/io/glb.py
jaxmesh/io/ply.py
jaxmesh/isosurface/__init__.py
jaxmesh/isosurface/marching_tetrahedra.py
jaxmesh/level_set/__init__.py
jaxmesh/level_set/crossings.py
jaxmesh/mesh/__init__.py
jaxmesh/mesh/simplex.py
jaxmesh/mesh/structured.py
jaxmesh/mesh/types.py
jaxmesh-0.2.0.dist-info/METADATA
jaxmesh-0.2.0.dist-info/WHEEL
jaxmesh-0.2.0.dist-info/RECORD
