Metadata-Version: 2.4
Name: jaxmesh
Version: 0.2.0
Summary: JAX-based mesh primitives and isosurface extraction
Project-URL: Homepage, https://github.com/Chiark-Collective/jax-mesh
Project-URL: Repository, https://github.com/Chiark-Collective/jax-mesh
Author-email: Liam Moore <liam@chiark.io>
License-Expression: MIT
Classifier: Development Status :: 4 - Beta
Classifier: Intended Audience :: Developers
Classifier: Intended Audience :: Science/Research
Classifier: License :: OSI Approved :: MIT License
Classifier: Programming Language :: Python :: 3
Classifier: Programming Language :: Python :: 3.10
Classifier: Programming Language :: Python :: 3.11
Classifier: Programming Language :: Python :: 3.12
Classifier: Topic :: Scientific/Engineering
Requires-Python: >=3.10
Requires-Dist: jax>=0.4.20
Requires-Dist: numpy>=1.24.0
Provides-Extra: dev
Requires-Dist: mypy; extra == 'dev'
Requires-Dist: pytest-xdist; extra == 'dev'
Requires-Dist: pytest>=7.0; extra == 'dev'
Requires-Dist: ruff; extra == 'dev'
